planetarium/__base__.py
planetarium/__init__.py
planetarium/license_reference.txt
Planetarium-0.0.1.dist-info/LICENSE
Planetarium-0.0.1.dist-info/METADATA
Planetarium-0.0.1.dist-info/WHEEL
Planetarium-0.0.1.dist-info/top_level.txt
Planetarium-0.0.1.dist-info/RECORD
