Metadata-Version: 2.1
Name: Planetarium
Version: 0.0.1
Summary: A Python / React planetarium in the brower, using Transcrypt and Pyact
Home-page: https://github.com/QQuick/Planetarium
Author: Jacques de Hooge
Author-email: jacques.de.hooge@qquick.org
License: Apache 2.0
Keywords: planetarium,transcrypt,pyact,react,python,browser
Platform: UNKNOWN
Classifier: Development Status :: 1 - Planning
Classifier: Intended Audience :: Developers
Classifier: Natural Language :: English
Classifier: License :: OSI Approved :: Apache Software License
Classifier: Topic :: Software Development :: Libraries :: Python Modules
Classifier: Operating System :: OS Independent
Classifier: Programming Language :: Python :: 3.9
Requires-Dist: transcrypt
Requires-Dist: pyact
